setup.py
gusbidis_calculation/Binomialdistribution.py
gusbidis_calculation/Gaussiandistribution.py
gusbidis_calculation/Generaldistribution.py
gusbidis_calculation/__init__.py
gusbidis_calculation.egg-info/PKG-INFO
gusbidis_calculation.egg-info/SOURCES.txt
gusbidis_calculation.egg-info/dependency_links.txt
gusbidis_calculation.egg-info/not-zip-safe
gusbidis_calculation.egg-info/top_level.txt