Metadata-Version: 1.0
Name: gusbidis-calculation
Version: 1.0
Summary: Gaussian and Binomial distributions
Home-page: UNKNOWN
Author: Christabel Ajaero
Author-email: ajaero.christabel@gmail.com
License: UNKNOWN
Platform: UNKNOWN
